cortex_cli/__init__.py
cortex_cli/cli/__init__.py
cortex_cli/cli/cli_api_base.py
cortex_cli/cli/cli_api_base_config.py
cortex_cli/cli/cli_multipart_upload.py
cortex_cli/cli/clients.py
cortex_cli/cli/configure.py
cortex_cli/cli/cortex_cli.py
cortex_cli/cli/generic_get.py
cortex_cli/cli/inferences.py
cortex_cli/cli/models.py
cortex_cli/cli/pipelines.py
cortex_cli/cli/api/__init__.py
cortex_cli/cli/api/github_api.py
cortex_cli/cli/api/http_api.py
cortex_cli/core/__init__.py
cortex_cli/core/cortex_data.py
cortex_cli/core/drift_checks.py
cortex_cli/core/ethics_checks.py
cortex_cli/core/secrets_manager.py
cortex_cli/core/models/__init__.py
cortex_cli/core/models/cortex_model.py
cortex_cli/model_templates/__init__.py
cortex_cli/model_templates/chatgpt_model/.gitignore
cortex_cli/model_templates/chatgpt_model/README.md
cortex_cli/model_templates/chatgpt_model/__init__.py
cortex_cli/model_templates/chatgpt_model/cookiecutter.json
cortex_cli/model_templates/chatgpt_model/requirements.txt
cortex_cli/model_templates/chatgpt_model/{{cookiecutter.model_repo}}/.gitignore
cortex_cli/model_templates/chatgpt_model/{{cookiecutter.model_repo}}/README.md
cortex_cli/model_templates/chatgpt_model/{{cookiecutter.model_repo}}/conda.yml
cortex_cli/model_templates/chatgpt_model/{{cookiecutter.model_repo}}/cortex.yml
cortex_cli/model_templates/chatgpt_model/{{cookiecutter.model_repo}}/data/.gitkeep
cortex_cli/model_templates/chatgpt_model/{{cookiecutter.model_repo}}/notebooks/.gitkeep
cortex_cli/model_templates/chatgpt_model/{{cookiecutter.model_repo}}/src/{{cookiecutter.__model_name}}/__init__.py
cortex_cli/model_templates/chatgpt_model/{{cookiecutter.model_repo}}/src/{{cookiecutter.__model_name}}/{{cookiecutter.__model_name}}.py
cortex_cli/model_templates/digits_model/.gitignore
cortex_cli/model_templates/digits_model/README.md
cortex_cli/model_templates/digits_model/__init__.py
cortex_cli/model_templates/digits_model/cookiecutter.json
cortex_cli-2.4.1.dist-info/METADATA
cortex_cli-2.4.1.dist-info/WHEEL
cortex_cli-2.4.1.dist-info/entry_points.txt
cortex_cli-2.4.1.dist-info/top_level.txt
cortex_cli-2.4.1.dist-info/RECORD
