Metadata-Version: 2.1
Name: cortex-cli
Version: 2.4.1
Summary: Nearly Human Cortex CLI for interacting with model functions.
Author: Nearly Human
Author-email: support@nearlyhuman.ai
Keywords: CLI,API,nearlyhuman,nearly human,cortex
Requires-Python: >=3.8.10
Requires-Dist: cortex-container-tools
Requires-Dist: cloudpickle ==2.1.0
Requires-Dist: cookiecutter
Requires-Dist: fairlearn
Requires-Dist: markdown
Requires-Dist: plumbum
Requires-Dist: prophet
Requires-Dist: pypdf
Requires-Dist: pyth3
Requires-Dist: python-doc
Requires-Dist: python-docx
